compass/virtuals_sdk/__init__.py
compass/virtuals_sdk/api_wrapper.py
compass/virtuals_sdk/config.py
compass/virtuals_sdk/py.typed
compass/virtuals_sdk/shared_defaults.py
compass/virtuals_sdk/simple_agent.py
compass/virtuals_sdk/simple_worker.py
compass/virtuals_sdk/wallet.py
compass_virtuals_sdk-0.1.84.dist-info/METADATA
compass_virtuals_sdk-0.1.84.dist-info/WHEEL
compass_virtuals_sdk-0.1.84.dist-info/RECORD
