Metadata-Version: 2.3
Name: compass.virtuals_sdk
Version: 0.1.84
Summary: 
Author: royalnine
Author-email: 17271567+royalnine@users.noreply.github.com
Requires-Python: >=3.10,<3.13
Classifier: Programming Language :: Python :: 3
Classifier: Programming Language :: Python :: 3.10
Classifier: Programming Language :: Python :: 3.11
Classifier: Programming Language :: Python :: 3.12
Requires-Dist: compass.api_client
Requires-Dist: game-sdk (>=0.1.3,<0.2.0)
Requires-Dist: python-dotenv (>=1.0.1,<2.0.0)
Requires-Dist: web3 (>=7.7.0,<8.0.0)
